[
  {
    "id": "0010D",
    "price": 10.0,
    "name": "Donation",
    "url": "/products.json"
  },
  {
    "id": "0020D",
    "price": 20.0,
    "name": "Donation",
    "url": "/products.json"
  },
  {
    "id": "0050D",
    "price": 50.0,
    "name": "Donation",
    "url": "/products.json"
  },
  {
    "id": "0100D",
    "price": 100.0,
    "name": "Donation",
    "url": "/products.json"
  },
  {
    "id": "1500D",
    "price": 1500.0,
    "name": "Donation",
    "url": "/products.json"
  },
  {
    "id": "2600C",
    "price": 25.0,
    "name": "26XX SIGINT/EW Challenge Coin",
    "url": "/products.json"
  },
  {
    "id": "2621P",
    "price": 10.0,
    "name": "2621 Pin",
    "url": "/products.json"
  },
  {
    "id": "2641P",
    "price": 10.0,
    "name": "2641 Pin",
    "url": "/products.json"
  },
  {
    "id": "2651P",
    "price": 10.0,
    "name": "2651 Pin",
    "url": "/products.json"
  },
  {
    "id": "26XXD",
    "price": 10.0,
    "name": "26XX Decal",
    "url": "/products.json"
  },
  {
    "id": "2651D",
    "price": 10.0,
    "name": "2651 Decal",
    "url": "/products.json"
  },
  {
    "id": "2602D",
    "price": 10.0,
    "name": "2602 Decal",
    "url": "/products.json"
  },
  {
    "id": "2629D",
    "price": 10.0,
    "name": "2629 Decal",
    "url": "/products.json"
  },
  {
    "id": "267XD",
    "price": 10.0,
    "name": "267X Decal",
    "url": "/products.json"
  },
  {
    "id": "2691D",
    "price": 10.0,
    "name": "2691 Decal",
    "url": "/products.json"
  },
  {
    "id": "0001C",
    "price": 15.0,
    "name": "Good Idea Fairy Coin",
    "url": "/products.json"
  },
  {
    "id": "1000S",
    "price": 1000.0,
    "name": "V.I.P. Corporate Sponsorship",
    "url": "/products.json"
  },
  {
    "id": "2500S",
    "price": 2500.0,
    "name": "Executive Corporate Sponsorship",
    "url": "/products.json"
  },
  {
    "id": "5000S",
    "price": 5000.0,
    "name": "Platinum Corporate Sponsorship",
    "url": "/products.json"
  },
  {
    "id": "1000E",
    "price": 10000.0,
    "name": "Elite Corporate Sponsorship",
    "url": "/products.json"
  }
]
